pymscada_milp-0.0.3.dist-info/METADATA
pymscada_milp-0.0.3.dist-info/WHEEL
pymscada_milp-0.0.3.dist-info/entry_points.txt
pymscada_milp-0.0.3.dist-info/licenses/LICENSE
pymscada_milp/__init__.py
pymscada_milp/__main__.py
pymscada_milp/demo/milp.yaml
pymscada_milp/kalmanfilter.py
pymscada_milp/main.py
pymscada_milp/matrix.py
pymscada_milp/misc.py
pymscada_milp/model.py
pymscada_milp/model_hyd.py
pymscada_milp-0.0.3.dist-info/RECORD
